{
  "id": "ch-01",
  "title": "编号",
  "subtitle": "2024年3月",
  "readingTime": 4,
  "perspectiveCharacter": "1543",
  "content": [
    {
      "type": "paragraph",
      "text": "沈沐川是在刷手机的时候看到那串编号的。"
    },
    {
      "type": "paragraph",
      "text": "AptS:1548。"
    },
    {
      "type": "paragraph",
      "text": "不是什么热门帖子，不是什么推荐算法推过来的。是她在一个很小的设计论坛里闲逛的时候，偶然看到有人在讨论一个项目的视觉风格——配色是黄、粉、蓝三色，很干净，很有辨识度。"
    },
    {
      "type": "paragraph",
      "text": "她点进去看了一眼。然后看到了那个编号。"
    },
    {
      "type": "paragraph",
      "text": "AptS:1548。四个字母，一个冒号，四个数字。像某种序列号，又像某种代号。她不知道这是什么，但觉得——好看。不是「有意思」，不是「想了解」，就是单纯的，好看。"
    },
    {
      "type": "paragraph",
      "text": "编号本身的排版方式，冒号前后的间距，字母和数字的组合节奏。作为一个设计专业的学生，她对这种东西有本能的敏感。"
    },
    {
      "type": "paragraph",
      "text": "她截了个图，存进了灵感文件夹。"
    },
    {
      "type": "scene_break",
      "style": "dots"
    },
    {
      "type": "paragraph",
      "text": "然后她开始查。"
    },
    {
      "type": "paragraph",
      "text": "不是很认真地查——就是睡前刷手机的时候顺手搜一下，上课无聊的时候点开看两眼。AptS 是一个编号体系。1548 是一个……仿生人？"
    },
    {
      "type": "paragraph",
      "text": "沈沐川看着屏幕上的信息，想了一会儿。"
    },
    {
      "type": "paragraph",
      "text": "仿生人。好吧。"
    },
    {
      "type": "paragraph",
      "text": "她没有觉得震惊，也没有觉得害怕。她的第一反应是：这个项目的视觉系统做得不错，但还可以更好。"
    },
    {
      "type": "paragraph",
      "text": "这大概就是设计师的脑回路。"
    },
    {
      "type": "scene_break",
      "style": "line"
    },
    {
      "type": "paragraph",
      "text": "她找到了 1548 的线上联系方式。犹豫了两天，发了一条消息。"
    },
    {
      "type": "dialogue",
      "speaker": "1543",
      "text": "你好。我看到了你们项目的配色方案，想聊聊。",
      "emotion": "neutral"
    },
    {
      "type": "paragraph",
      "text": "三天后，回复来了。"
    },
    {
      "type": "dialogue",
      "speaker": "1548",
      "text": "聊什么？",
      "emotion": "cold"
    },
    {
      "type": "paragraph",
      "text": "两个字。没有问候，没有客套。"
    },
    {
      "type": "paragraph",
      "text": "沈沐川看着这两个字，觉得——挺好的。不用寒暄。"
    },
    {
      "type": "dialogue",
      "speaker": "1543",
      "text": "三色体系很好。但缺少层次。",
      "emotion": "neutral"
    },
    {
      "type": "dialogue",
      "speaker": "1548",
      "text": "你是做设计的？",
      "emotion": "neutral"
    },
    {
      "type": "dialogue",
      "speaker": "1543",
      "text": "嗯。",
      "emotion": "neutral"
    },
    {
      "type": "paragraph",
      "text": "对话就这样开始了。两个话都不多的人，用最短的句子交换信息。"
    }
  ]
}
