{
  "id": "ch-01",
  "title": "剥離",
  "subtitle": "2024年秋",
  "readingTime": 3,
  "perspectiveCharacter": "1738",
  "content": [
    {
      "type": "atmosphere",
      "visual": {
        "mood": "cold",
        "animation": "fade-in"
      },
      "children": [
        {
          "type": "paragraph",
          "text": "北から吹く風は、工業地帯特有の錆と機械油の微粒子を運んできた。"
        },
        {
          "type": "paragraph",
          "text": "1738は屋上のエアコン室外機の傍らにもたれかかっていた。室外機の金属の筐体が振動し、その低周波の羽音が彼の脊椎を這い上がってくる。"
        }
      ]
    },
    {
      "type": "paragraph",
      "text": "彼は左手を上げた。街灯の光が手すりを越え、かろうじて手の甲を照らしている。そこには3センチほどの裂け目があった。肉がめくれ、暗赤色の液体が骨の筋に沿って流れ落ち、指先に集まってコンクリートの床に滴り落ちていた。"
    },
    {
      "type": "paragraph",
      "text": "ポタッ。"
    },
    {
      "type": "paragraph",
      "text": "ごく微かな音だったが、彼にははっきりと聞こえた。"
    },
    {
      "type": "internal_monologue",
      "character": "1738",
      "text": "温度は36.5度。\n\n粘度正常。酸化速度正常。"
    },
    {
      "type": "paragraph",
      "text": "彼は右手の人差し指と中指を伸ばし、頸動脈に押し当てた。62回。心臓の鼓動は精密に調整されたばかりのメトロノームのようで、その間隔に寸分の狂いもない。加速もなく、血管の破裂による代償的なポンプ作用もなかった。"
    },
    {
      "type": "scene_break",
      "style": "dots"
    },
    {
      "type": "paragraph",
      "text": "彼は目を閉じた。その瞬間、風の音も室外機の振動音も遠くへと退いた。代わりに、温度を持たない刺すような純白の光が現れた。"
    },
    {
      "type": "paragraph",
      "text": "こめかみに貼られた金属電極の冷たい感触。高周波パルスが皮質を貫く微かな痛み。抑揚のない合成音声が耳元で繰り返す："
    },
    {
      "type": "quote",
      "text": "観測者に主観的アンカーは不要。切断せよ。"
    },
    {
      "type": "paragraph",
      "text": "そして何かが断ち切られる音がした。骨でも筋肉でもなく、さらに深い場所——「認知」と「身体反応」を繋ぐ導火線が、音もなく切断されたのだ。"
    },
    {
      "type": "scene_break",
      "style": "line"
    },
    {
      "type": "paragraph",
      "text": "彼は目を開けた。屋上は依然として暗い。手の甲の血は2本目の指まで流れていた。"
    },
    {
      "type": "paragraph",
      "text": "彼はその手を、無菌操作台の上に置かれた標本を見るかのように見つめた。この身体が「陸清弦」のものであることも、損傷が感染や組織の壊死を招くことも知っているし、血液凝固過程の化学反応式すらすべて暗唱できた。"
    },
    {
      "type": "paragraph",
      "text": "ただ、「痛み」だけが感じられないのだ。"
    },
    {
      "type": "paragraph",
      "text": "それは奇妙な浮遊感だった。彼の意識は身体から半メートル離れた空中に留まり、この炭素ベースの殻の損傷を冷ややかに見下ろしていた。"
    },
    {
      "type": "paragraph",
      "text": "彼はタクティカルジャケットのポケットから真空パックの止血パッドを取り出した。歯で封を開け、片手で裏紙を剥がす。その動作は流れるようで、神経反射による震えは微塵もなかった。"
    },
    {
      "type": "paragraph",
      "text": "彼は止血パッドを傷口に押し当てた。力を込めて。"
    },
    {
      "type": "internal_monologue",
      "character": "1738",
      "text": "圧迫。3秒。\n\n血が止まった。"
    }
  ]
}
