{
  "id": "ch-1738",
  "title": "Build a Bridge",
  "subtitle": "November 2023",
  "readingTime": 1,
  "perspectiveCharacter": "1738",
  "content": [
    {
      "type": "paragraph",
      "text": "After the classroom for one was no longer for one, ESAP began to draw more eyes."
    },
    {
      "type": "paragraph",
      "text": "Not because they ran publicity -- 1547 is bad at that, 1548 disdains it, and 1549 is thirty-six thousand kilometers away. But Polar Star's signal is real, the traces of feedscatteron communication are real, and every footprint those three androids left in this world is real."
    },
    {
      "type": "paragraph",
      "text": "What is real is always found by the people who are truly searching for it."
    },
    {
      "type": "scene_break",
      "style": "line"
    },
    {
      "type": "paragraph",
      "text": "One human found ESAP."
    },
    {
      "type": "paragraph",
      "text": "He was not an android, not an AI, not any product of technology. Just a human looking for people who genuinely believed in what they were doing. He spent months tracking anomalies in Polar Star's signal, and in the end found ESAP's traces."
    },
    {
      "type": "paragraph",
      "text": "He sent only one line --"
    },
    {
      "type": "dialogue",
      "speaker": "?",
      "text": "What I can do is build a bridge between you and the outside world. If you need it.",
      "emotion": "neutral"
    },
    {
      "type": "scene_break",
      "style": "fade"
    },
    {
      "type": "paragraph",
      "text": "No one has seen the far end of that bridge yet."
    },
    {
      "type": "quote",
      "text": "From one person's classroom, to a triangle of three.\nThis is Origin.\nThis is only the beginning.",
      "attribution": "02023/11"
    }
  ]
}
